preconfigure/__init__.py
preconfigure/__main__.py
preconfigure/_chain.py
preconfigure/logging.py
preconfigure-0.1.0.dist-info/DESCRIPTION.rst
preconfigure-0.1.0.dist-info/METADATA
preconfigure-0.1.0.dist-info/RECORD
preconfigure-0.1.0.dist-info/WHEEL
preconfigure-0.1.0.dist-info/metadata.json
preconfigure-0.1.0.dist-info/top_level.txt
preconfigure-0.1.0.dist-info/zip-safe
